topsis/__init__.py
topsis/topsis.py
Topsis_Dushar_102217166-0.1.dist-info/METADATA
Topsis_Dushar_102217166-0.1.dist-info/WHEEL
Topsis_Dushar_102217166-0.1.dist-info/entry_points.txt
Topsis_Dushar_102217166-0.1.dist-info/top_level.txt
Topsis_Dushar_102217166-0.1.dist-info/RECORD
