Metadata-Version: 2.2
Name: Topsis-Dushar-102217166
Version: 0.1
Summary: A Python package to implement the Topsis method
Home-page: https://github.com/dusharkhatri/Topsis-Dushar-102217166
Author: Dushar Khatri
Author-email: dkhatri_be22@thapar.edu
Classifier: Programming Language :: Python :: 3
Classifier: Operating System :: OS Independent
Requires-Dist: pandas
Requires-Dist: numpy
Dynamic: author
Dynamic: author-email
Dynamic: classifier
Dynamic: description
Dynamic: description-content-type
Dynamic: home-page
Dynamic: requires-dist
Dynamic: summary
